AUTHORS
LICENSE
MANIFEST.in
README.rst
setup.py
django_js_error_logging.egg-info/PKG-INFO
django_js_error_logging.egg-info/SOURCES.txt
django_js_error_logging.egg-info/dependency_links.txt
django_js_error_logging.egg-info/not-zip-safe
django_js_error_logging.egg-info/top_level.txt
jserrorlogging/__init__.py
jserrorlogging/admin.py
jserrorlogging/app_settings.py
jserrorlogging/context_processors.py
jserrorlogging/forms.py
jserrorlogging/models.py
jserrorlogging/receivers.py
jserrorlogging/signals.py
jserrorlogging/tests.py
jserrorlogging/urls.py
jserrorlogging/utils.py
jserrorlogging/views.py
jserrorlogging/migrations/0001_initial.py
jserrorlogging/migrations/__init__.py
jserrorlogging/static/jserrorlogging/grunt.js
jserrorlogging/static/jserrorlogging/js/logger.js
jserrorlogging/static/jserrorlogging/js/logger.min.js
jserrorlogging/templates/jserrorlogging/logging.html
jserrorlogging/templates/jserrorlogging/email/body.txt
jserrorlogging/templates/jserrorlogging/email/subject.txt
jserrorlogging/templates/jserrorlogging/includes/script.html
jserrorlogging/templates/jserrorlogging/includes/script_with_user.html