Metadata-Version: 1.0
Name: django-js-error-logging
Version: 0.1.1
Summary: Logging Client-Side JavaScript errors for Django
Home-page: http://github.com/moqada/django-js-error-logging/
Author: Masahiko Okada
Author-email: moqada@gmail.com
License: BSD License
Keywords: django,javascript,logging,notify
Platform: UNKNOWN
Classifier: Development Status :: 4 - Beta
Classifier: Environment :: Plugins
Classifier: Framework :: Django
Classifier: Intended Audience :: Developers
Classifier: License :: OSI Approved :: BSD License
Classifier: Programming Language :: Python
Classifier: Topic :: Software Development :: Libraries :: Python Modules
